xarray_sql/__init__.py
xarray_sql/core.py
xarray_sql/df.py
xarray_sql/df_integrationtest.py
xarray_sql/df_test.py
xarray_sql/sql.py
xarray_sql/sql_test.py
xarray_sql-0.1.1.dist-info/licenses/LICENSE
xarray_sql-0.1.1.dist-info/METADATA
xarray_sql-0.1.1.dist-info/WHEEL
xarray_sql-0.1.1.dist-info/top_level.txt
xarray_sql-0.1.1.dist-info/RECORD
