Metadata-Version: 2.4
Name: xarray_sql
Version: 0.1.1
Summary: Querry Xarray with SQL.
Author-email: Alexander Merose <al@merose.com>
License: Apache-2.0
Project-URL: Homepage, https://github.com/alxmrs/xarray-sql
Project-URL: Issues, https://github.com/alxmrs/xarray-sql/issues
Classifier: Development Status :: 4 - Beta
Classifier: Intended Audience :: Science/Research
Classifier: Intended Audience :: Developers
Classifier: Intended Audience :: Information Technology
Classifier: License :: OSI Approved :: Apache Software License
Classifier: Operating System :: MacOS :: MacOS X
Classifier: Operating System :: Microsoft :: Windows
Classifier: Operating System :: POSIX
Classifier: Programming Language :: Python :: 3.9
Classifier: Programming Language :: Python :: 3.10
Classifier: Programming Language :: Python :: 3.11
Classifier: Programming Language :: Python :: 3.12
Classifier: Programming Language :: Python :: 3.13
Classifier: Topic :: Scientific/Engineering :: Atmospheric Science
Classifier: Topic :: Database :: Front-Ends
Requires-Python: >=3.9
License-File: LICENSE
Requires-Dist: dask>=2024.8.0
Requires-Dist: datafusion>=47.0.0
Requires-Dist: xarray>=2024.7.0
Provides-Extra: test
Requires-Dist: pytest; extra == "test"
Requires-Dist: xarray[io]; extra == "test"
Requires-Dist: gcsfs; extra == "test"
Dynamic: license-file
